ngrp/__init__.py
ngrp/cli.py
ngrp/config_writer.py
ngrp/metainfo.py
ngrp/ngrp.py
ngrp/templates/HttpReverseProxyTemplate.py
ngrp/templates/HttpsReverseProxyTemplate.py
ngrp/templates/StaticPageHttpTemplate.py
ngrp/templates/StaticPageHttpsTemplate.py
ngrp/templates/Template.py
ngrp/templates/__init__.py
ngrp-0.3.3.dist-info/METADATA
ngrp-0.3.3.dist-info/RECORD
ngrp-0.3.3.dist-info/WHEEL
ngrp-0.3.3.dist-info/entry_points.txt
ngrp-0.3.3.dist-info/top_level.txt
