Metadata-Version: 2.1
Name: ngrp
Version: 0.3.3
Summary: A handy tool that configures nginx reverse proxy for you
Home-page: https://github.com/klausweiss/ngrp
Author: Mikołaj Biel
License: UNKNOWN
Platform: UNKNOWN
Requires-Python: >=3
Requires-Dist: click (==6.7)
